{
  "fetchedAt": "2026-04-28 12:45:46",
  "totalTickers": 88,
  "successCount": 88,
  "failCount": 0,
  "data": {
    "AADI": {
      "ticker": "AADI",
      "yahooTicker": "AADI.JK",
      "date": "2026-04-28",
      "open": 11000.0,
      "high": 11250.0,
      "low": 10875.0,
      "close": 10900.0,
      "volume": 11168800
    },
    "ACES": {
      "ticker": "ACES",
      "yahooTicker": "ACES.JK",
      "date": "2026-04-28",
      "open": 386.0,
      "high": 388.0,
      "low": 366.0,
      "close": 368.0,
      "volume": 48127900
    },
    "ADMR": {
      "ticker": "ADMR",
      "yahooTicker": "ADMR.JK",
      "date": "2026-04-28",
      "open": 1875.0,
      "high": 1885.0,
      "low": 1840.0,
      "close": 1845.0,
      "volume": 22469000
    },
    "ADRO": {
      "ticker": "ADRO",
      "yahooTicker": "ADRO.JK",
      "date": "2026-04-28",
      "open": 2430.0,
      "high": 2470.0,
      "low": 2400.0,
      "close": 2410.0,
      "volume": 71464700
    },
    "AKRA": {
      "ticker": "AKRA",
      "yahooTicker": "AKRA.JK",
      "date": "2026-04-28",
      "open": 1560.0,
      "high": 1560.0,
      "low": 1525.0,
      "close": 1530.0,
      "volume": 15167900
    },
    "AMMN": {
      "ticker": "AMMN",
      "yahooTicker": "AMMN.JK",
      "date": "2026-04-28",
      "open": 5400.0,
      "high": 5425.0,
      "low": 5125.0,
      "close": 5125.0,
      "volume": 14238400
    },
    "AMRT": {
      "ticker": "AMRT",
      "yahooTicker": "AMRT.JK",
      "date": "2026-04-28",
      "open": 1415.0,
      "high": 1415.0,
      "low": 1310.0,
      "close": 1325.0,
      "volume": 52415900
    },
    "ANTM": {
      "ticker": "ANTM",
      "yahooTicker": "ANTM.JK",
      "date": "2026-04-28",
      "open": 4120.0,
      "high": 4290.0,
      "low": 3940.0,
      "close": 4040.0,
      "volume": 171366200
    },
    "ARTO": {
      "ticker": "ARTO",
      "yahooTicker": "ARTO.JK",
      "date": "2026-04-28",
      "open": 1295.0,
      "high": 1325.0,
      "low": 1285.0,
      "close": 1320.0,
      "volume": 6155900
    },
    "ASII": {
      "ticker": "ASII",
      "yahooTicker": "ASII.JK",
      "date": "2026-04-28",
      "open": 6150.0,
      "high": 6200.0,
      "low": 6025.0,
      "close": 6025.0,
      "volume": 36965000
    },
    "AUTO": {
      "ticker": "AUTO",
      "yahooTicker": "AUTO.JK",
      "date": "2026-04-28",
      "open": 2620.0,
      "high": 2660.0,
      "low": 2600.0,
      "close": 2640.0,
      "volume": 2316400
    },
    "AVIA": {
      "ticker": "AVIA",
      "yahooTicker": "AVIA.JK",
      "date": "2026-04-28",
      "open": 388.0,
      "high": 394.0,
      "low": 378.0,
      "close": 388.0,
      "volume": 18263300
    },
    "BBCA": {
      "ticker": "BBCA",
      "yahooTicker": "BBCA.JK",
      "date": "2026-04-28",
      "open": 6025.0,
      "high": 6075.0,
      "low": 5950.0,
      "close": 6000.0,
      "volume": 174091200
    },
    "BBNI": {
      "ticker": "BBNI",
      "yahooTicker": "BBNI.JK",
      "date": "2026-04-28",
      "open": 3750.0,
      "high": 3790.0,
      "low": 3680.0,
      "close": 3790.0,
      "volume": 31602700
    },
    "BBRI": {
      "ticker": "BBRI",
      "yahooTicker": "BBRI.JK",
      "date": "2026-04-28",
      "open": 3050.0,
      "high": 3080.0,
      "low": 3020.0,
      "close": 3070.0,
      "volume": 232596600
    },
    "BBTN": {
      "ticker": "BBTN",
      "yahooTicker": "BBTN.JK",
      "date": "2026-04-28",
      "open": 1390.0,
      "high": 1410.0,
      "low": 1350.0,
      "close": 1395.0,
      "volume": 24586400
    },
    "BFIN": {
      "ticker": "BFIN",
      "yahooTicker": "BFIN.JK",
      "date": "2026-04-28",
      "open": 795.0,
      "high": 815.0,
      "low": 775.0,
      "close": 795.0,
      "volume": 45436500
    },
    "BMRI": {
      "ticker": "BMRI",
      "yahooTicker": "BMRI.JK",
      "date": "2026-04-28",
      "open": 4420.0,
      "high": 4480.0,
      "low": 4350.0,
      "close": 4430.0,
      "volume": 246361500
    },
    "BNGA": {
      "ticker": "BNGA",
      "yahooTicker": "BNGA.JK",
      "date": "2026-04-28",
      "open": 1695.0,
      "high": 1705.0,
      "low": 1680.0,
      "close": 1705.0,
      "volume": 15200300
    },
    "BRIS": {
      "ticker": "BRIS",
      "yahooTicker": "BRIS.JK",
      "date": "2026-04-28",
      "open": 1840.0,
      "high": 1845.0,
      "low": 1765.0,
      "close": 1800.0,
      "volume": 34719000
    },
    "BRMS": {
      "ticker": "BRMS",
      "yahooTicker": "BRMS.JK",
      "date": "2026-04-28",
      "open": 830.0,
      "high": 835.0,
      "low": 800.0,
      "close": 815.0,
      "volume": 126847800
    },
    "BRPT": {
      "ticker": "BRPT",
      "yahooTicker": "BRPT.JK",
      "date": "2026-04-28",
      "open": 2030.0,
      "high": 2120.0,
      "low": 1980.0,
      "close": 2010.0,
      "volume": 152232900
    },
    "BSDE": {
      "ticker": "BSDE",
      "yahooTicker": "BSDE.JK",
      "date": "2026-04-28",
      "open": 795.0,
      "high": 825.0,
      "low": 780.0,
      "close": 825.0,
      "volume": 16698900
    },
    "BTPS": {
      "ticker": "BTPS",
      "yahooTicker": "BTPS.JK",
      "date": "2026-04-28",
      "open": 1010.0,
      "high": 1015.0,
      "low": 1005.0,
      "close": 1015.0,
      "volume": 3244300
    },
    "BUKA": {
      "ticker": "BUKA",
      "yahooTicker": "BUKA.JK",
      "date": "2026-04-28",
      "open": 162.0,
      "high": 163.0,
      "low": 157.0,
      "close": 157.0,
      "volume": 121852100
    },
    "BUMI": {
      "ticker": "BUMI",
      "yahooTicker": "BUMI.JK",
      "date": "2026-04-28",
      "open": 228.0,
      "high": 230.0,
      "low": 220.0,
      "close": 228.0,
      "volume": 1800570700
    },
    "CMRY": {
      "ticker": "CMRY",
      "yahooTicker": "CMRY.JK",
      "date": "2026-04-28",
      "open": 4540.0,
      "high": 4550.0,
      "low": 4490.0,
      "close": 4550.0,
      "volume": 3747800
    },
    "CPIN": {
      "ticker": "CPIN",
      "yahooTicker": "CPIN.JK",
      "date": "2026-04-28",
      "open": 4070.0,
      "high": 4090.0,
      "low": 4000.0,
      "close": 4090.0,
      "volume": 2414500
    },
    "CTRA": {
      "ticker": "CTRA",
      "yahooTicker": "CTRA.JK",
      "date": "2026-04-28",
      "open": 700.0,
      "high": 710.0,
      "low": 690.0,
      "close": 700.0,
      "volume": 5580600
    },
    "DSNG": {
      "ticker": "DSNG",
      "yahooTicker": "DSNG.JK",
      "date": "2026-04-28",
      "open": 1855.0,
      "high": 1855.0,
      "low": 1715.0,
      "close": 1770.0,
      "volume": 20003500
    },
    "DSSA": {
      "ticker": "DSSA",
      "yahooTicker": "DSSA.JK",
      "date": "2026-04-28",
      "open": 1850.0,
      "high": 1895.0,
      "low": 1750.0,
      "close": 1765.0,
      "volume": 43261800
    },
    "ELSA": {
      "ticker": "ELSA",
      "yahooTicker": "ELSA.JK",
      "date": "2026-04-28",
      "open": 795.0,
      "high": 840.0,
      "low": 780.0,
      "close": 830.0,
      "volume": 189633100
    },
    "EMTK": {
      "ticker": "EMTK",
      "yahooTicker": "EMTK.JK",
      "date": "2026-04-28",
      "open": 830.0,
      "high": 850.0,
      "low": 795.0,
      "close": 825.0,
      "volume": 55908100
    },
    "ENRG": {
      "ticker": "ENRG",
      "yahooTicker": "ENRG.JK",
      "date": "2026-04-28",
      "open": 1715.0,
      "high": 1760.0,
      "low": 1680.0,
      "close": 1750.0,
      "volume": 104402000
    },
    "ERAA": {
      "ticker": "ERAA",
      "yahooTicker": "ERAA.JK",
      "date": "2026-04-28",
      "open": 418.0,
      "high": 418.0,
      "low": 398.0,
      "close": 416.0,
      "volume": 70524500
    },
    "ESSA": {
      "ticker": "ESSA",
      "yahooTicker": "ESSA.JK",
      "date": "2026-04-28",
      "open": 960.0,
      "high": 975.0,
      "low": 930.0,
      "close": 960.0,
      "volume": 88497000
    },
    "EXCL": {
      "ticker": "EXCL",
      "yahooTicker": "EXCL.JK",
      "date": "2026-04-28",
      "open": 3150.0,
      "high": 3160.0,
      "low": 3030.0,
      "close": 3030.0,
      "volume": 3360500
    },
    "GGRM": {
      "ticker": "GGRM",
      "yahooTicker": "GGRM.JK",
      "date": "2026-04-28",
      "open": 14575.0,
      "high": 16325.0,
      "low": 14575.0,
      "close": 16175.0,
      "volume": 3120800
    },
    "GJTL": {
      "ticker": "GJTL",
      "yahooTicker": "GJTL.JK",
      "date": "2026-04-28",
      "open": 1180.0,
      "high": 1200.0,
      "low": 1175.0,
      "close": 1195.0,
      "volume": 16315900
    },
    "GOTO": {
      "ticker": "GOTO",
      "yahooTicker": "GOTO.JK",
      "date": "2026-04-28",
      "open": 53.0,
      "high": 54.0,
      "low": 53.0,
      "close": 53.0,
      "volume": 1376193600
    },
    "HEAL": {
      "ticker": "HEAL",
      "yahooTicker": "HEAL.JK",
      "date": "2026-04-28",
      "open": 1195.0,
      "high": 1200.0,
      "low": 1170.0,
      "close": 1170.0,
      "volume": 2999800
    },
    "HRUM": {
      "ticker": "HRUM",
      "yahooTicker": "HRUM.JK",
      "date": "2026-04-28",
      "open": 1010.0,
      "high": 1020.0,
      "low": 995.0,
      "close": 1005.0,
      "volume": 8021600
    },
    "ICBP": {
      "ticker": "ICBP",
      "yahooTicker": "ICBP.JK",
      "date": "2026-04-28",
      "open": 6900.0,
      "high": 6950.0,
      "low": 6750.0,
      "close": 6775.0,
      "volume": 5589600
    },
    "INCO": {
      "ticker": "INCO",
      "yahooTicker": "INCO.JK",
      "date": "2026-04-28",
      "open": 6875.0,
      "high": 6950.0,
      "low": 6775.0,
      "close": 6800.0,
      "volume": 19233500
    },
    "INDF": {
      "ticker": "INDF",
      "yahooTicker": "INDF.JK",
      "date": "2026-04-28",
      "open": 6900.0,
      "high": 6925.0,
      "low": 6750.0,
      "close": 6825.0,
      "volume": 12570200
    },
    "INDY": {
      "ticker": "INDY",
      "yahooTicker": "INDY.JK",
      "date": "2026-04-28",
      "open": 3810.0,
      "high": 3880.0,
      "low": 3730.0,
      "close": 3770.0,
      "volume": 13137700
    },
    "INKP": {
      "ticker": "INKP",
      "yahooTicker": "INKP.JK",
      "date": "2026-04-28",
      "open": 9900.0,
      "high": 9900.0,
      "low": 9650.0,
      "close": 9675.0,
      "volume": 5098800
    },
    "INTP": {
      "ticker": "INTP",
      "yahooTicker": "INTP.JK",
      "date": "2026-04-28",
      "open": 5250.0,
      "high": 5275.0,
      "low": 5075.0,
      "close": 5150.0,
      "volume": 776000
    },
    "ISAT": {
      "ticker": "ISAT",
      "yahooTicker": "ISAT.JK",
      "date": "2026-04-28",
      "open": 2030.0,
      "high": 2030.0,
      "low": 1930.0,
      "close": 1950.0,
      "volume": 14611500
    },
    "ITMG": {
      "ticker": "ITMG",
      "yahooTicker": "ITMG.JK",
      "date": "2026-04-28",
      "open": 24900.0,
      "high": 25600.0,
      "low": 24600.0,
      "close": 25475.0,
      "volume": 2374700
    },
    "JPFA": {
      "ticker": "JPFA",
      "yahooTicker": "JPFA.JK",
      "date": "2026-04-28",
      "open": 2530.0,
      "high": 2530.0,
      "low": 2340.0,
      "close": 2350.0,
      "volume": 21364800
    },
    "JSMR": {
      "ticker": "JSMR",
      "yahooTicker": "JSMR.JK",
      "date": "2026-04-28",
      "open": 3210.0,
      "high": 3220.0,
      "low": 3170.0,
      "close": 3170.0,
      "volume": 1191300
    },
    "KIJA": {
      "ticker": "KIJA",
      "yahooTicker": "KIJA.JK",
      "date": "2026-04-28",
      "open": 185.0,
      "high": 189.0,
      "low": 182.0,
      "close": 186.0,
      "volume": 75047000
    },
    "KLBF": {
      "ticker": "KLBF",
      "yahooTicker": "KLBF.JK",
      "date": "2026-04-28",
      "open": 875.0,
      "high": 885.0,
      "low": 865.0,
      "close": 885.0,
      "volume": 56885700
    },
    "KPIG": {
      "ticker": "KPIG",
      "yahooTicker": "KPIG.JK",
      "date": "2026-04-28",
      "open": 110.0,
      "high": 112.0,
      "low": 108.0,
      "close": 109.0,
      "volume": 38041000
    },
    "LSIP": {
      "ticker": "LSIP",
      "yahooTicker": "LSIP.JK",
      "date": "2026-04-28",
      "open": 1785.0,
      "high": 1800.0,
      "low": 1675.0,
      "close": 1690.0,
      "volume": 16498600
    },
    "MAPA": {
      "ticker": "MAPA",
      "yahooTicker": "MAPA.JK",
      "date": "2026-04-28",
      "open": 635.0,
      "high": 660.0,
      "low": 620.0,
      "close": 625.0,
      "volume": 26111400
    },
    "MAPI": {
      "ticker": "MAPI",
      "yahooTicker": "MAPI.JK",
      "date": "2026-04-28",
      "open": 1330.0,
      "high": 1335.0,
      "low": 1275.0,
      "close": 1290.0,
      "volume": 17445300
    },
    "MBMA": {
      "ticker": "MBMA",
      "yahooTicker": "MBMA.JK",
      "date": "2026-04-28",
      "open": 685.0,
      "high": 710.0,
      "low": 670.0,
      "close": 705.0,
      "volume": 132576400
    },
    "MDKA": {
      "ticker": "MDKA",
      "yahooTicker": "MDKA.JK",
      "date": "2026-04-28",
      "open": 3480.0,
      "high": 3490.0,
      "low": 3400.0,
      "close": 3420.0,
      "volume": 26659900
    },
    "MEDC": {
      "ticker": "MEDC",
      "yahooTicker": "MEDC.JK",
      "date": "2026-04-28",
      "open": 1735.0,
      "high": 1755.0,
      "low": 1705.0,
      "close": 1725.0,
      "volume": 48217700
    },
    "MIKA": {
      "ticker": "MIKA",
      "yahooTicker": "MIKA.JK",
      "date": "2026-04-28",
      "open": 2050.0,
      "high": 2060.0,
      "low": 1970.0,
      "close": 1980.0,
      "volume": 1985900
    },
    "MNCN": {
      "ticker": "MNCN",
      "yahooTicker": "MNCN.JK",
      "date": "2026-04-28",
      "open": 250.0,
      "high": 254.0,
      "low": 242.0,
      "close": 248.0,
      "volume": 26708400
    },
    "MTEL": {
      "ticker": "MTEL",
      "yahooTicker": "MTEL.JK",
      "date": "2026-04-28",
      "open": 515.0,
      "high": 515.0,
      "low": 500.0,
      "close": 515.0,
      "volume": 10370500
    },
    "MYOR": {
      "ticker": "MYOR",
      "yahooTicker": "MYOR.JK",
      "date": "2026-04-28",
      "open": 1840.0,
      "high": 1845.0,
      "low": 1785.0,
      "close": 1800.0,
      "volume": 12660900
    },
    "NCKL": {
      "ticker": "NCKL",
      "yahooTicker": "NCKL.JK",
      "date": "2026-04-28",
      "open": 1140.0,
      "high": 1150.0,
      "low": 1120.0,
      "close": 1125.0,
      "volume": 33218500
    },
    "PANI": {
      "ticker": "PANI",
      "yahooTicker": "PANI.JK",
      "date": "2026-04-28",
      "open": 8450.0,
      "high": 8650.0,
      "low": 8325.0,
      "close": 8550.0,
      "volume": 3043200
    },
    "PGAS": {
      "ticker": "PGAS",
      "yahooTicker": "PGAS.JK",
      "date": "2026-04-28",
      "open": 1895.0,
      "high": 1935.0,
      "low": 1895.0,
      "close": 1905.0,
      "volume": 14316400
    },
    "PGEO": {
      "ticker": "PGEO",
      "yahooTicker": "PGEO.JK",
      "date": "2026-04-28",
      "open": 1015.0,
      "high": 1025.0,
      "low": 1005.0,
      "close": 1025.0,
      "volume": 11947000
    },
    "PNBN": {
      "ticker": "PNBN",
      "yahooTicker": "PNBN.JK",
      "date": "2026-04-28",
      "open": 1025.0,
      "high": 1025.0,
      "low": 990.0,
      "close": 1010.0,
      "volume": 4831400
    },
    "PNLF": {
      "ticker": "PNLF",
      "yahooTicker": "PNLF.JK",
      "date": "2026-04-28",
      "open": 250.0,
      "high": 250.0,
      "low": 242.0,
      "close": 246.0,
      "volume": 35208100
    },
    "PTBA": {
      "ticker": "PTBA",
      "yahooTicker": "PTBA.JK",
      "date": "2026-04-28",
      "open": 2910.0,
      "high": 2920.0,
      "low": 2880.0,
      "close": 2890.0,
      "volume": 9708300
    },
    "PTRO": {
      "ticker": "PTRO",
      "yahooTicker": "PTRO.JK",
      "date": "2026-04-28",
      "open": 5400.0,
      "high": 5700.0,
      "low": 5200.0,
      "close": 5500.0,
      "volume": 128630300
    },
    "PWON": {
      "ticker": "PWON",
      "yahooTicker": "PWON.JK",
      "date": "2026-04-28",
      "open": 334.0,
      "high": 336.0,
      "low": 326.0,
      "close": 330.0,
      "volume": 54375700
    },
    "RAJA": {
      "ticker": "RAJA",
      "yahooTicker": "RAJA.JK",
      "date": "2026-04-28",
      "open": 4380.0,
      "high": 4450.0,
      "low": 4290.0,
      "close": 4350.0,
      "volume": 26335600
    },
    "RATU": {
      "ticker": "RATU",
      "yahooTicker": "RATU.JK",
      "date": "2026-04-28",
      "open": 6325.0,
      "high": 6700.0,
      "low": 6200.0,
      "close": 6575.0,
      "volume": 14564000
    },
    "SCMA": {
      "ticker": "SCMA",
      "yahooTicker": "SCMA.JK",
      "date": "2026-04-28",
      "open": 262.0,
      "high": 264.0,
      "low": 256.0,
      "close": 262.0,
      "volume": 21144600
    },
    "SIDO": {
      "ticker": "SIDO",
      "yahooTicker": "SIDO.JK",
      "date": "2026-04-28",
      "open": 496.0,
      "high": 498.0,
      "low": 494.0,
      "close": 496.0,
      "volume": 4890200
    },
    "SMGR": {
      "ticker": "SMGR",
      "yahooTicker": "SMGR.JK",
      "date": "2026-04-28",
      "open": 2040.0,
      "high": 2070.0,
      "low": 2000.0,
      "close": 2040.0,
      "volume": 12275400
    },
    "SMRA": {
      "ticker": "SMRA",
      "yahooTicker": "SMRA.JK",
      "date": "2026-04-28",
      "open": 304.0,
      "high": 310.0,
      "low": 302.0,
      "close": 304.0,
      "volume": 21384100
    },
    "SRTG": {
      "ticker": "SRTG",
      "yahooTicker": "SRTG.JK",
      "date": "2026-04-28",
      "open": 1815.0,
      "high": 1885.0,
      "low": 1790.0,
      "close": 1835.0,
      "volume": 23570100
    },
    "TAPG": {
      "ticker": "TAPG",
      "yahooTicker": "TAPG.JK",
      "date": "2026-04-28",
      "open": 2030.0,
      "high": 2040.0,
      "low": 1980.0,
      "close": 1990.0,
      "volume": 18660900
    },
    "TKIM": {
      "ticker": "TKIM",
      "yahooTicker": "TKIM.JK",
      "date": "2026-04-28",
      "open": 8775.0,
      "high": 8900.0,
      "low": 8575.0,
      "close": 8575.0,
      "volume": 677900
    },
    "TLKM": {
      "ticker": "TLKM",
      "yahooTicker": "TLKM.JK",
      "date": "2026-04-28",
      "open": 2790.0,
      "high": 2820.0,
      "low": 2750.0,
      "close": 2820.0,
      "volume": 146311100
    },
    "TOWR": {
      "ticker": "TOWR",
      "yahooTicker": "TOWR.JK",
      "date": "2026-04-28",
      "open": 482.0,
      "high": 484.0,
      "low": 474.0,
      "close": 476.0,
      "volume": 14186600
    },
    "UNTR": {
      "ticker": "UNTR",
      "yahooTicker": "UNTR.JK",
      "date": "2026-04-28",
      "open": 30675.0,
      "high": 30750.0,
      "low": 30100.0,
      "close": 30175.0,
      "volume": 2181700
    },
    "UNVR": {
      "ticker": "UNVR",
      "yahooTicker": "UNVR.JK",
      "date": "2026-04-28",
      "open": 1525.0,
      "high": 1545.0,
      "low": 1485.0,
      "close": 1485.0,
      "volume": 42672500
    },
    "WIFI": {
      "ticker": "WIFI",
      "yahooTicker": "WIFI.JK",
      "date": "2026-04-28",
      "open": 2350.0,
      "high": 2370.0,
      "low": 2270.0,
      "close": 2330.0,
      "volume": 12279600
    }
  }
}